rectify/__init__.py
rectify/image.py
rectify/main.py
rectify/palette.py
tests/__init__.py
tests/test_cli.py
tests/test_image.py
tests/test_palette.py
rectify-2.2.dist-info/LICENSE
rectify-2.2.dist-info/METADATA
rectify-2.2.dist-info/WHEEL
rectify-2.2.dist-info/entry_points.txt
rectify-2.2.dist-info/top_level.txt
rectify-2.2.dist-info/RECORD
