Metadata-Version: 2.1
Name: rectify
Version: 2.2
Summary: Bars generator
Home-page: https://gitlab.com/jenx/rectify/
Author: Ivana Kellyerova
Author-email: ivana.kellyerova@rectify.amarion.net
License: MIT
Keywords: image,bars,stripe,avatar,generator,rectangle,colors
Platform: UNKNOWN
Classifier: Development Status :: 4 - Beta
Classifier: Intended Audience :: End Users/Desktop
Classifier: License :: OSI Approved :: MIT License
Classifier: Operating System :: OS Independent
Classifier: Programming Language :: Python
Classifier: Programming Language :: Python :: 3
Classifier: Programming Language :: Python :: 3.4
Classifier: Programming Language :: Python :: 3.5
Classifier: Programming Language :: Python :: 3.6
Classifier: Programming Language :: Python :: 3.7
Classifier: Programming Language :: Python :: 3 :: Only
Classifier: Topic :: Artistic Software
Classifier: Topic :: Multimedia :: Graphics
Requires-Dist: docopt (>=0.6.2)
Requires-Dist: Pillow (>=5.3.0)
Provides-Extra: docs
Requires-Dist: sphinx ; extra == 'docs'
Requires-Dist: sphinxcontrib-napoleon ; extra == 'docs'
